mydocs/__init__.py
mydocs/functions_value.py
mydocs/index.py
mydocs/main.py
mydocs/running.py
mydocs_streamlit-2.0.0.dist-info/METADATA
mydocs_streamlit-2.0.0.dist-info/WHEEL
mydocs_streamlit-2.0.0.dist-info/entry_points.txt
mydocs_streamlit-2.0.0.dist-info/top_level.txt
mydocs_streamlit-2.0.0.dist-info/RECORD
