Metadata-Version: 2.1
Name: mydocs-streamlit
Version: 2.0.0
Summary: My first Python package
Home-page: 
Author: Jaswanth Anupoju
Author-email: ajaswanth791@gmail.com
Classifier: Programming Language :: Python :: 3
Classifier: License :: OSI Approved :: MIT License
Classifier: Operating System :: OS Independent
Requires-Python: >=3.6
Requires-Dist: streamlit>=1.40.0
